  // main class examples/euler/euler04

  // access flags 0xA
  private static reverse(I)I
    ICONST_0
    ISTORE 1
    ICONST_0
    ISTORE 2
   L0
    ILOAD 0
    ICONST_0
    IF_ICMPLE L1
    ILOAD 0
    BIPUSH 10
    IREM
    ISTORE 1
    ILOAD 2
    BIPUSH 10
    IMUL
    ILOAD 1
    IADD
    ISTORE 2
    ILOAD 0
    BIPUSH 10
    IDIV
    ISTORE 0
    GOTO L0
   L1
    ILOAD 2
    IRETURN
    MAXSTACK = 100
    MAXLOCALS = 100

  // access flags 0xA
  private static isPalindrome(I)Z
    ILOAD 0
    ILOAD 0
    INVOKESTATIC examples/euler/euler04.reverse (I)I
    IF_ICMPEQ L2
    ICONST_0
    GOTO L3
   L2
    ICONST_1
   L3
    IRETURN
    MAXSTACK = 100
    MAXLOCALS = 100

  // access flags 0x9
  public static main([Ljava/lang/String;)V
    SIPUSH 999
    ISTORE 1
    ILOAD 1
    ISTORE 2
    ILOAD 1
    ISTORE 3
    ILOAD 2
    ILOAD 3
    IMUL
    ISTORE 4
    ICONST_0
    ISTORE 5
    ICONST_0
    ISTORE 6
    ICONST_0
    ISTORE 7
   L4
    ILOAD 2
    ICONST_0
    IF_ICMPGT L5
    ICONST_0
    GOTO L6
   L5
    ICONST_1
   L6
    IFLE L7
    ILOAD 3
    ICONST_0
    IF_ICMPGT L8
    ICONST_0
    GOTO L9
   L8
    ICONST_1
   L9
    IFLE L7
    ILOAD 2
    ILOAD 3
    IMUL
    ISTORE 4
    ILOAD 4
    INVOKESTATIC examples/euler/euler04.isPalindrome (I)Z
    IFEQ L10
    ILOAD 4
    ILOAD 5
    IF_ICMPLE L11
    ILOAD 4
    ISTORE 5
    ILOAD 2
    ISTORE 6
    ILOAD 3
    ISTORE 7
   L11
   L10
    IINC 2 -1
    ILOAD 2
    ICONST_0
    IF_ICMPNE L12
    ILOAD 1
    ISTORE 2
    IINC 3 -1
   L12
    GOTO L4
   L7
    GETSTATIC java/lang/System.out : Ljava/io/PrintStream;
    ILOAD 5
    INVOKEVIRTUAL java/io/PrintStream.println (I)V
    RETURN
    MAXSTACK = 1000
    MAXLOCALS = 1000
}
